{
  "$schema": "https://developer.microsoft.com/json-schemas/fabric/item/report/definition/visualContainer/2.6.0/schema.json",
  "name": "mb_logo_slot",
  "position": {
    "x": 1090,
    "y": 18,
    "z": 0,
    "width": 245,
    "height": 74,
    "tabOrder": 11
  },
  "visual": {
    "visualType": "textbox",
    "objects": {
      "general": [
        {
          "properties": {
            "paragraphs": [
              {
                "textRuns": [
                  {
                    "value": "MAPLE BEAR",
                    "textStyle": {
                      "fontFamily": "Georgia",
                      "fontSize": "16pt",
                      "fontWeight": "bold",
                      "color": "#A9191F"
                    }
                  }
                ],
                "horizontalTextAlignment": "center"
              },
              {
                "textRuns": [
                  {
                    "value": "Espaço reservado para a logo",
                    "textStyle": {
                      "fontFamily": "Segoe UI",
                      "fontSize": "9pt",
                      "color": "#6A584A"
                    }
                  }
                ],
                "horizontalTextAlignment": "center"
              }
            ]
          }
        }
      ]
    },
    "visualContainerObjects": {
      "background": [
        {
          "properties": {
            "color": {
              "solid": {
                "color": {
                  "expr": {
                    "Literal": {
                      "Value": "'#FFF7EA'"
                    }
                  }
                }
              }
            }
          }
        }
      ],
      "border": [
        {
          "properties": {
            "show": {
              "expr": {
                "Literal": {
                  "Value": "true"
                }
              }
            },
            "color": {
              "solid": {
                "color": {
                  "expr": {
                    "Literal": {
                      "Value": "'#D4A62A'"
                    }
                  }
                }
              }
            }
          }
        }
      ],
      "visualHeader": [
        {
          "properties": {
            "show": {
              "expr": {
                "Literal": {
                  "Value": "false"
                }
              }
            }
          }
        }
      ]
    }
  }
}
